telescope_distance/__init__.py
telescope_distance/telescope.py
telescope_distance/clustering/__init__.py
telescope_distance/clustering/agglomerative.py
telescope_distance/clustering/kmedoids.py
telescope_distance/clustering/pist_clustering.py
telescope_distance/examples/__init__.py
telescope_distance/examples/dependent_series_clustering.py
telescope_distance/examples/pist_clustering.py
telescope_distance/generators/__init__.py
telescope_distance/generators/generators.py
telescope_distance/utils/__init__.py
telescope_distance/utils/utils.py
telescope_distance-0.0.5.dist-info/LICENSE
telescope_distance-0.0.5.dist-info/METADATA
telescope_distance-0.0.5.dist-info/WHEEL
telescope_distance-0.0.5.dist-info/top_level.txt
telescope_distance-0.0.5.dist-info/RECORD
