Metadata-Version: 2.1
Name: telescope-distance
Version: 0.0.5
Summary: Time-series clustering based on telescope distance
Home-page: https://github.com/soheil-arab/telescope-distance
Author: Ali Arabzadeh
Author-email: s.arabzadeh@lancaster.ac.uk
License: MIT
License-File: LICENSE
Requires-Dist: numpy (>=1.18)
Requires-Dist: sklearn (~=0.0)
Requires-Dist: scikit-learn
Requires-Dist: scipy
Requires-Dist: setuptools (~=47.1.0)
Requires-Dist: kmedoids
Requires-Dist: PyChest (~=1.22)
